pyTSL.pyd
tspytsl-1.9.dist-info/METADATA
tspytsl-1.9.dist-info/WHEEL
tspytsl-1.9.dist-info/RECORD
