Metadata-Version: 1.2
Name: tspytsl
Version: 1.9
Summary: Python module for TSL
Home-page: https://py3k.cn/pyTSL/
Author: Wei guangjing
Author-email: vcc@py3k.cn
License: Freeware
Download-URL: https://py3k.cn/pyTSL/download/
Platform: UNKNOWN
Classifier: Development Status :: 5 - Production/Stable
Classifier: Intended Audience :: Developers
Classifier: Intended Audience :: Information Technology
Classifier: License :: Freeware
Classifier: Operating System :: OS Independent
Classifier: Programming Language :: Python
Classifier: Programming Language :: Python :: 3
